LICENSE
MANIFEST.in
README.md
setup.py
libdevpro_h31.egg-info/PKG-INFO
libdevpro_h31.egg-info/SOURCES.txt
libdevpro_h31.egg-info/dependency_links.txt
libdevpro_h31.egg-info/not-zip-safe
libdevpro_h31.egg-info/requires.txt
libdevpro_h31.egg-info/top_level.txt
libpythonpro/__init__.py
libpythonpro/github_api.py